Helpingai_T3/__init__.py
Helpingai_T3-0.2.dist-info/LICENSE
Helpingai_T3-0.2.dist-info/METADATA
Helpingai_T3-0.2.dist-info/WHEEL
Helpingai_T3-0.2.dist-info/top_level.txt
Helpingai_T3-0.2.dist-info/RECORD
